---
title: 循环
date: 2019-01-19 19:28:39
tags: java
---


> for 循环 和 while 循环

```
public class ForAndWhile {

    public static void main(String[] args) {
        for (int i = 0; i < 5; i++) {

        }

        int j = 0;
        while (j < 5) {
            j++;
        }
    }
}
```

<!--more-->

for 循环 和 while 循环的字节码是一样的
```
$ javap -c ForAndWhile.class
Compiled from "ForAndWhile.java"
public class com.yangyang.java.ForAndWhile {
  public com.yangyang.java.ForAndWhile();
    Code:
       0: aload_0
       1: invokespecial #1                  // Method java/lang/Object."<init>":()V
       4: return

  public static void main(java.lang.String[]);
    Code:
       0: iconst_0
       1: istore_1
       2: iload_1
       3: iconst_5
       4: if_icmpge     13
       7: iinc          1, 1
      10: goto          2


      13: iconst_0
      14: istore_1
      15: iload_1
      16: iconst_5
      17: if_icmpge     26
      20: iinc          1, 1
      23: goto          15
      26: return
}

```